Abinde.py
Abinde-2.5.dist-info/LICENSE
Abinde-2.5.dist-info/METADATA
Abinde-2.5.dist-info/WHEEL
Abinde-2.5.dist-info/top_level.txt
Abinde-2.5.dist-info/RECORD
