Metadata-Version: 2.1
Name: Abinde
Version: 2.5
Summary: Abinde is an easy-to-use python module for pygame.
Home-page: https://github.com/Abinde-Game-Dev
Author: _TheRealPenguin
License: MIT License        
Project-URL: Homepage, https://github.com/Abinde-Game-Dev/Abinde
Project-URL: Bug Tracker, https://github.com/Abinde-Game-Dev/Abinde/issues
Keywords: game python lightweight open-source raspberry-pi mac linux games image game-engine simple game-development game-2d pygame help-wanted easy-to-use easy open-source-project good-first-issue pygame-games pygame-game
Classifier: Development Status :: 2 - Pre-Alpha
Classifier: License :: OSI Approved :: MIT License
Classifier: Natural Language :: English
Classifier: Programming Language :: Python :: 3 :: Only
Classifier: Topic :: Games/Entertainment
Classifier: Topic :: Utilities
Classifier: Intended Audience :: Developers
Requires-Python: >=3.7
License-File: LICENSE
Requires-Dist: pygame (>=2.1.2)
Requires-Dist: pillow
Requires-Dist: importlib-metadata ; python_version >= "3.8"
